icon_resize/__init__.py
icon_resize-0.3.0.dist-info/METADATA
icon_resize-0.3.0.dist-info/WHEEL
icon_resize-0.3.0.dist-info/entry_points.txt
icon_resize-0.3.0.dist-info/licenses/LICENSE
icon_resize-0.3.0.dist-info/RECORD
