Metadata-Version: 2.4
Name: icon-resize
Version: 0.3.0
Summary: CLI to create lossless icons in multiple sizes
Project-URL: repository, https://github.com/hoishing/icon-resize
Project-URL: license, https://opensource.org/licenses/MIT
Author-email: Kelvin Ng <hoishing@gmail.com>
License: MIT
License-File: LICENSE
Keywords: cli,png,resize
Requires-Python: >=3.12
Requires-Dist: typer>=0.15.2
